email_master/__init__.py
email_master/attachments.py
email_master/compat.py
email_master/exceptions.py
email_master/messages.py
email_master/parser.py
email_master/rfc3156.py
email_master/util.py
email_master/eml/__init__.py
email_master/eml/message.py
email_master/eml/parser.py
email_master/msg/__init__.py
email_master/msg/parser.py
email_master/pgp/__init__.py
email_master/pgp/config.py
email_master/pgp/wrapper.py
email_master-0.7.2.dist-info/METADATA
email_master-0.7.2.dist-info/WHEEL
email_master-0.7.2.dist-info/top_level.txt
email_master-0.7.2.dist-info/RECORD
