Metadata-Version: 2.2
Name: email-master
Version: 0.7.2
Summary: Master Email Parsing Package
Author: Swimlane
Author-email: info@swimlane.com
Keywords: utilities,email,parsing,eml,msg
Requires-Dist: pendulum>=2.1.2
Requires-Dist: compressed-rtf==1.0.5
Requires-Dist: extract_msg==0.23.2
Requires-Dist: PGPy==0.6.0
Dynamic: author
Dynamic: author-email
Dynamic: description
Dynamic: keywords
Dynamic: requires-dist
Dynamic: summary
